detprocess/__init__.py
detprocess/_version.py
detprocess/core/__init__.py
detprocess/core/algorithms.py
detprocess/core/didv.py
detprocess/core/eventbuilder.py
detprocess/core/filterdata.py
detprocess/core/ivsweep.py
detprocess/core/noise.py
detprocess/core/noisemodel.py
detprocess/core/oftrigger.py
detprocess/core/rawdata.py
detprocess/core/salting.py
detprocess/core/template.py
detprocess/process/__init__.py
detprocess/process/config.py
detprocess/process/features.py
detprocess/process/filterprocess.py
detprocess/process/ivprocess.py
detprocess/process/processing_data.py
detprocess/process/randoms.py
detprocess/process/triggers.py
detprocess/utils/__init__.py
detprocess/utils/utils.py
detprocess-0.6.0.dist-info/licenses/LICENSE
detprocess-0.6.0.dist-info/METADATA
detprocess-0.6.0.dist-info/WHEEL
detprocess-0.6.0.dist-info/top_level.txt
detprocess-0.6.0.dist-info/RECORD
