Metadata-Version: 2.4
Name: detprocess
Version: 0.6.0
Summary: Detector Data Processing Package
Home-page: https://github.com/spice-herald/detprocess
Author: Bruno Serfass, Samuel Watkins
Author-email: serfass@berkeley.edu, samwatkins@berkeley.edu
License-File: LICENSE
Requires-Dist: numpy
Requires-Dist: scipy
Requires-Dist: matplotlib
Requires-Dist: pyyaml
Requires-Dist: qetpy>=1.8.3
Requires-Dist: pandas
Requires-Dist: pytesdaq>=0.4.5
Requires-Dist: scikit-image
Requires-Dist: iminuit>=2
Requires-Dist: seaborn
Requires-Dist: humanfriendly
Requires-Dist: vaex
Dynamic: author
Dynamic: author-email
Dynamic: description
Dynamic: description-content-type
Dynamic: home-page
Dynamic: license-file
Dynamic: requires-dist
Dynamic: summary
